myasicAPI/__init__.py
myasicAPI-0.2.5.dist-info/LICENSE
myasicAPI-0.2.5.dist-info/METADATA
myasicAPI-0.2.5.dist-info/WHEEL
myasicAPI-0.2.5.dist-info/top_level.txt
myasicAPI-0.2.5.dist-info/RECORD
