Metadata-Version: 2.1
Name: myasicAPI
Version: 0.2.5
Summary: API for MyAsic project
Home-page: https://github.com/MiningManufacture/MyAsic.git
Author: @MyAsic
Author-email: baikal-interspace@eyandex.com
License: UNKNOWN
Platform: UNKNOWN
Classifier: Programming Language :: Python :: 3
Classifier: License :: OSI Approved :: MIT License
Classifier: Operating System :: OS Independent
Requires-Python: >=3.6
